octavvs/__init__.py
octavvs/clustering.py
octavvs/decomposition.py
octavvs/icons_src_rc.py
octavvs/launcher.py
octavvs/make_icons.py
octavvs/mcr_als.py
octavvs/preprocessing.py
octavvs/algorithms/__init__.py
octavvs/algorithms/atm_correction.py
octavvs/algorithms/baseline.py
octavvs/algorithms/correction.py
octavvs/algorithms/decomposition.py
octavvs/algorithms/decomposition_working.py
octavvs/algorithms/decomposition_working_2.py
octavvs/algorithms/imputation.py
octavvs/algorithms/mie_correction.py
octavvs/algorithms/normalization.py
octavvs/algorithms/ptir.py
octavvs/algorithms/util.py
octavvs/decomp/__init__.py
octavvs/decomp/decomposition.ui
octavvs/decomp/decompworker.py
octavvs/decomp/plotwidget.py
octavvs/decomp/settings_table.ui
octavvs/io/__init__.py
octavvs/io/decompositiondata.py
octavvs/io/image.py
octavvs/io/omnicreader.py
octavvs/io/opusreader.py
octavvs/io/parameters.py
octavvs/io/ptirreader.py
octavvs/io/spectraldata.py
octavvs/mcr/__init__.py
octavvs/mcr/about.ui
octavvs/mcr/clustering_ui.ui
octavvs/mcr/ftir_function.py
octavvs/mcr/mcr_final_loc.ui
octavvs/mcr/mcr_roi_sub.ui
octavvs/mcr/mpl.py
octavvs/mcr/table_ui.ui
octavvs/prep/__init__.py
octavvs/prep/create_reference.ui
octavvs/prep/dataplotwidget.py
octavvs/prep/mcadvanced.ui
octavvs/prep/octavvs_prep.icns
octavvs/prep/octavvs_prep.ico
octavvs/prep/octavvs_prep_48.ico
octavvs/prep/preprocessing_ui.ui
octavvs/prep/prepworker.py
octavvs/prep/scadvanced.ui
octavvs/pymcr_new/__init__.py
octavvs/pymcr_new/constraints.py
octavvs/pymcr_new/metrics.py
octavvs/pymcr_new/regressors.py
octavvs/reference_spectra/CAS_bg_10perc_crub7.mat
octavvs/reference_spectra/CAS_wh_5perc.mat
octavvs/reference_spectra/CMC_bg_10perc_crub7.mat
octavvs/reference_spectra/CMC_wh_5perc.mat
octavvs/reference_spectra/LIG_bg_10perc_crub7.mat
octavvs/reference_spectra/LIG_wh_5perc.mat
octavvs/reference_spectra/PEC_bg_10perc_crub7.mat
octavvs/reference_spectra/Q_table.mat
octavvs/reference_spectra/__init__.py
octavvs-0.1.31.dist-info/licenses/LICENSE
octavvs-0.1.31.dist-info/METADATA
octavvs-0.1.31.dist-info/WHEEL
octavvs-0.1.31.dist-info/entry_points.txt
octavvs-0.1.31.dist-info/top_level.txt
octavvs-0.1.31.dist-info/RECORD
