Metadata-Version: 2.4
Name: octavvs
Version: 0.1.31
Summary: Open Chemometrics Toolkit for Analysis and Visualization of Vibrational Spectroscopy data
Home-page: https://github.com/ctroein/octavvs
Author: Syahril Siregar, Carl Troein, Michiel Op De Beeck et al.
Author-email: carl@thep.lu.se
Classifier: Programming Language :: Python :: 3
Classifier: License :: OSI Approved :: MIT License
Classifier: Operating System :: OS Independent
Requires-Python: >=3.6
License-File: LICENSE
Requires-Dist: numpy
Requires-Dist: scipy
Requires-Dist: matplotlib
Requires-Dist: scikit-learn
Requires-Dist: pyshortcuts
Requires-Dist: pandas
Requires-Dist: pillow
Requires-Dist: pymatreader
Requires-Dist: dill
Requires-Dist: threadpoolctl>=3.1.0
Requires-Dist: statsmodels
Requires-Dist: scikit-image
Dynamic: author
Dynamic: author-email
Dynamic: classifier
Dynamic: description
Dynamic: description-content-type
Dynamic: home-page
Dynamic: license-file
Dynamic: requires-dist
Dynamic: requires-python
Dynamic: summary
